cwl2puml/__about__.py
cwl2puml/__init__.py
cwl2puml/cli.py
cwl2puml/templates/activity.puml
cwl2puml/templates/class.puml
cwl2puml/templates/component.puml
cwl2puml/templates/sequence.puml
cwl2puml/templates/state.puml
cwl2puml-0.32.0.dist-info/METADATA
cwl2puml-0.32.0.dist-info/WHEEL
cwl2puml-0.32.0.dist-info/entry_points.txt
cwl2puml-0.32.0.dist-info/licenses/LICENSE
cwl2puml-0.32.0.dist-info/licenses/NOTICE
cwl2puml-0.32.0.dist-info/RECORD
