Metadata-Version: 2.4
Name: cwl2puml
Version: 0.32.0
Summary: CWL Worflows processor to generate PlantUML diagrams
Project-URL: Documentation, https://github.com/Terradue/cwl2puml#readme
Project-URL: Issues, https://github.com/Terradue/cwl2puml/issues
Project-URL: Source, https://github.com/Terradue/cwl2puml
Author-email: Fabrice Brito <info@terradue.com>, Simone Tripodi <info@terradue.com>
License-Expression: MIT
License-File: LICENSE
License-File: NOTICE
Classifier: Development Status :: 4 - Beta
Classifier: Programming Language :: Python
Classifier: Programming Language :: Python :: 3.9
Classifier: Programming Language :: Python :: 3.10
Classifier: Programming Language :: Python :: 3.11
Classifier: Programming Language :: Python :: 3.12
Classifier: Programming Language :: Python :: 3.13
Classifier: Programming Language :: Python :: Implementation :: CPython
Classifier: Programming Language :: Python :: Implementation :: PyPy
Requires-Python: >=3.8
Requires-Dist: click>=8.2.1
Requires-Dist: cwl-loader>=0.14.0
Requires-Dist: cwl-utils>=0.40
Requires-Dist: cwltool>=3.1.20250715140722
Requires-Dist: jinja2>=3.1.6
Requires-Dist: loguru
Requires-Dist: plantuml
